{
   "title" : "Decode JSON",
   "ID" : 20,
   "buttons" :
   [ 
    	    {
		"title" : "https://play.google.com/store/apps/details?id=com.QuizGame.millionnaire",
		"image" : "https://raw.githubusercontent.com/adbuzzllc/casual-games/master/dragonn.jpg"
	 },
	 {
		"title" : "https://play.google.com/store/apps/details?id=com.kGoNuibe.deliveryboy.cityicecream.virtuallifegame",
		"image" : "https://raw.githubusercontent.com/adbuzzllc/casual-games/master/2.jpg"
	 },	

	   	    {
		"title" : "https://play.google.com/store/apps/details?id=com.kGoNuib.impossible.bmx.bicycle",
		"image" : "https://raw.githubusercontent.com/adbuzzllc/casual-games/master/slither.png"
	 },
	 {
		"title" : "https://play.google.com/store/apps/details?id=com.nGoNuib.SuperHero.StuntBike.Race",
		"image" : "https://raw.githubusercontent.com/gadeceex/NobGames/master/1.png"
	 }	 
     
   ]
}
